{"dependencies":[{"name":"lodash-es/clamp","loc":{"line":1,"column":18}}],"generated":{"js":"\"use strict\";\n\nObject.defineProperty(exports, \"__esModule\", {\n  value: true\n});\nexports.range = range;\n\nvar _clamp = require(\"lodash-es/clamp\");\n\nvar _clamp2 = _interopRequireDefault(_clamp);\n\nfunction _interopRequireDefault(obj) { return obj && obj.__esModule ? obj : { default: obj }; }\n\nfunction range(min, max) {\n  if (min === void 0) {\n    min = -Infinity;\n  }\n  if (max === void 0) {\n    max = Infinity;\n  }\n  return function (proto, key) {\n    var alias = \"_\" + key;\n    Object.defineProperty(proto, key, {\n      get: function () {\n        return this[alias];\n      },\n      set: function (val) {\n        Object.defineProperty(this, alias, {\n          value: (0, _clamp2.default)(val, min, max),\n          enumerable: false,\n          writable: true,\n          configurable: true\n        });\n      },\n      enumerable: true,\n      configurable: true\n    });\n  };\n}\n//# sourceMappingURL=range.js.map"},"hash":"f08b534b42ebc5c850b7aae601cdcb10"}